admesh.so
.libsadmesh/libadmesh-92df0739.so.1.0.0
admesh-0.98.9.dist-info/WHEEL
admesh-0.98.9.dist-info/top_level.txt
admesh-0.98.9.dist-info/METADATA
admesh-0.98.9.dist-info/RECORD
